pytest_plus/__init__.py
pytest_plus/_version.py
pytest_plus/py.typed
pytest_plus-0.8.0.dist-info/LICENSE
pytest_plus-0.8.0.dist-info/METADATA
pytest_plus-0.8.0.dist-info/WHEEL
pytest_plus-0.8.0.dist-info/entry_points.txt
pytest_plus-0.8.0.dist-info/top_level.txt
pytest_plus-0.8.0.dist-info/RECORD
