Metadata-Version: 2.2
Name: pytest-plus
Version: 0.8.0
Summary: PyTest Plus Plugin :: extends pytest functionality
Author-email: Sorin Sbarnea <sorin.sbarnea@gmail.com>
Maintainer-email: Sorin Sbarnea <sorin.sbarnea@gmail.com>
License: MIT
Project-URL: changelog, https://github.com/pytest-dev/pytest-plus/releases
Project-URL: homepage, https://github.com/pytest-dev/pytest-plus
Project-URL: repository, https://github.com/pytest-dev/pytest-plus
Keywords: testing,pytest,plugin
Classifier: Development Status :: 5 - Production/Stable
Classifier: Environment :: Console
Classifier: Framework :: Pytest
Classifier: Intended Audience :: Developers
Classifier: Intended Audience :: Information Technology
Classifier: Intended Audience :: System Administrators
Classifier: License :: OSI Approved :: MIT License
Classifier: Natural Language :: English
Classifier: Operating System :: OS Independent
Classifier: Programming Language :: Python :: 3 :: Only
Classifier: Programming Language :: Python :: 3
Classifier: Programming Language :: Python :: 3.10
Classifier: Programming Language :: Python :: 3.11
Classifier: Programming Language :: Python :: 3.12
Classifier: Programming Language :: Python :: 3.13
Classifier: Programming Language :: Python
Classifier: Topic :: Software Development :: Quality Assurance
Classifier: Topic :: Software Development :: Testing
Classifier: Topic :: System :: Systems Administration
Classifier: Topic :: Utilities
Requires-Python: >=3.10
License-File: LICENSE
Requires-Dist: pytest>=7.4.2
Provides-Extra: test
Requires-Dist: coverage>=7.0.0; extra == "test"
Requires-Dist: pytest-html; extra == "test"
